data_pypeline-0.1.4.dist-info/LICENSE.txt
data_pypeline-0.1.4.dist-info/METADATA
data_pypeline-0.1.4.dist-info/RECORD
data_pypeline-0.1.4.dist-info/WHEEL
data_pypeline-0.1.4.dist-info/top_level.txt
pypeline/__init__.py
pypeline/_db.py
pypeline/off_heap.py
pypeline/pypeline.py
