Metadata-Version: 2.1
Name: data-pypeline
Version: 0.1.4
Summary: Pypeline is a data pipeline builder library.
Home-page: https://github.com/austinv11/pypeline
Author: austinv11
Author-email: austinv11@gmail.com
License: Apache License 2.0
Project-URL: Bug Reports, https://github.com/austinv11/pypeline/issues
Project-URL: Source, https://github.com/austinv11/pypeline/
Keywords: data pipeline pypeline
Platform: UNKNOWN
Classifier: Programming Language :: Python :: 3
Classifier: Programming Language :: Python :: 3.6
Classifier: Programming Language :: Python :: 3.7
Classifier: License :: OSI Approved :: Apache Software License
Classifier: Framework :: AsyncIO
Classifier: Topic :: Scientific/Engineering
Classifier: Topic :: Software Development :: Libraries :: Application Frameworks
Classifier: Topic :: Utilities
Classifier: Operating System :: OS Independent
Classifier: Development Status :: 3 - Alpha
Requires-Dist: xxhash
Requires-Dist: billiard
Requires-Dist: dill
Requires-Dist: filelock
Requires-Dist: Plyvel; sys_platform != "win32"
Requires-Dist: ujson; sys_platform != "win32"
Requires-Dist: uvloop; sys_platform != "win32"
